chatlib/__init__.py
chatlib/base.py
chatlib/date_tools.py
chatlib/line.py
chatlib/whatsapp.py
pychatlib-0.2.0.dist-info/LICENSE
pychatlib-0.2.0.dist-info/METADATA
pychatlib-0.2.0.dist-info/WHEEL
pychatlib-0.2.0.dist-info/top_level.txt
pychatlib-0.2.0.dist-info/RECORD
