Metadata-Version: 2.1
Name: pychatlib
Version: 0.2.0
Summary: Provides functionality to read messaging/chat application exports.
Home-page: https://github.com/lahdjirayhan/pychatlib
Author: Rayhan Lahdji
License: BSD 3-clause
Platform: UNKNOWN
Classifier: Development Status :: 1 - Planning
Classifier: Intended Audience :: Developers
Classifier: Intended Audience :: Science/Research
